lineup_widget/__init__.py
lineup_widget/_version.py
lineup_widget/lineup.py
lineup_widget/static/0a90cd2d51265d96e0f3e4480b0eb95b.ttf
lineup_widget/static/201222e909b56a6ffec90fee21cac911.svg
lineup_widget/static/extension.js
lineup_widget/static/f1c1c66afd1f3de4dabdd1a95b7962ad.eot
lineup_widget/static/index.js
lineup_widget/static/index.js.map
lineup_widget-4.0.0.data/data/etc/jupyter/nbconfig/notebook.d/lineup_widget.json
lineup_widget-4.0.0.data/data/share/jupyter/nbextensions/lineup_widget/0a90cd2d51265d96e0f3e4480b0eb95b.ttf
lineup_widget-4.0.0.data/data/share/jupyter/nbextensions/lineup_widget/201222e909b56a6ffec90fee21cac911.svg
lineup_widget-4.0.0.data/data/share/jupyter/nbextensions/lineup_widget/extension.js
lineup_widget-4.0.0.data/data/share/jupyter/nbextensions/lineup_widget/f1c1c66afd1f3de4dabdd1a95b7962ad.eot
lineup_widget-4.0.0.data/data/share/jupyter/nbextensions/lineup_widget/index.js
lineup_widget-4.0.0.data/data/share/jupyter/nbextensions/lineup_widget/index.js.map
lineup_widget-4.0.0.dist-info/LICENSE.txt
lineup_widget-4.0.0.dist-info/METADATA
lineup_widget-4.0.0.dist-info/WHEEL
lineup_widget-4.0.0.dist-info/top_level.txt
lineup_widget-4.0.0.dist-info/RECORD
