Metadata-Version: 2.1
Name: lineup-widget
Version: 4.0.0
Summary: Wrapper around the LineUp.js library for multi attribute rankings
Home-page: https://github.com/lineupjs/lineup_widget
Author: Samuel Gratzl
Author-email: sam@sgratzl.com
License: MIT
Keywords: ipython,jupyter,widgets,lineup,ranking
Platform: Linux
Platform: Mac OS X
Platform: Windows
Classifier: Development Status :: 4 - Beta
Classifier: Framework :: Jupyter
Classifier: Intended Audience :: Developers
Classifier: Intended Audience :: Science/Research
Classifier: License :: OSI Approved :: MIT License
Classifier: Topic :: Multimedia :: Graphics
Classifier: Programming Language :: Python :: 3.3
Classifier: Programming Language :: Python :: 3.4
Classifier: Programming Language :: Python :: 3.5
Classifier: Programming Language :: Python :: 3.6
Classifier: Programming Language :: Python :: 3.7
Requires-Dist: ipywidgets (>=7.0.0)
Requires-Dist: pandas (>=0.18.0)
